{
	"methods": {
		"acme_newOrderTest": {
			"timeStamp": "2020-05-09T05:39:47.000Z",
			"attributes": {
				"shared": true,
				"invisible": false
			}
		},
		"acme_readme": {
			"timeStamp": "2020-05-09T05:39:47.000Z",
			"attributes": {
				"shared": true,
				"invisible": false
			}
		},
		"acme__jswKeyInfosSet": {
			"timeStamp": "2020-10-09T16:36:55.527Z",
			"attributes": {
				"invisible": true,
				"shared": false
			}
		},
		"acme__httpServerRequestIsSsl": {
			"timeStamp": "2020-05-09T05:39:47.000Z",
			"attributes": {
				"invisible": true,
				"shared": false
			}
		},
		"TXT_lineSepGet": {
			"timeStamp": "2020-05-09T05:39:48.000Z",
			"attributes": {
				"invisible": true,
				"preemptive": "capable",
				"shared": false
			}
		},
		"acme_certCurrentGet": {
			"timeStamp": "2020-05-09T05:39:47.000Z",
			"attributes": {
				"shared": true,
				"invisible": false
			}
		},
		"acme_webServerStart": {
			"timeStamp": "2020-07-30T09:08:51.000Z",
			"attributes": {
				"shared": true,
				"invisible": false
			}
		},
		"acme__domainReverseTest": {
			"timeStamp": "2020-05-09T05:39:46.000Z",
			"attributes": {
				"invisible": true,
				"shared": false
			}
		},
		"TXT_rtrim": {
			"timeStamp": "2020-05-09T05:39:48.000Z",
			"attributes": {
				"invisible": true,
				"preemptive": "capable",
				"shared": false
			}
		},
		"acme__domainExtractFromUrl": {
			"timeStamp": "2020-05-09T05:39:46.000Z",
			"attributes": {
				"invisible": true,
				"shared": false
			}
		},
		"ENV_versionStr": {
			"timeStamp": "2020-05-09T05:39:47.000Z",
			"attributes": {
				"invisible": true,
				"preemptive": "capable",
				"shared": false
			}
		},
		"acme__errorReset": {
			"timeStamp": "2020-05-09T05:39:46.000Z",
			"attributes": {
				"invisible": true,
				"shared": false
			}
		},
		"acme_dateParse": {
			"timeStamp": "2020-05-09T05:39:47.000Z",
			"attributes": {
				"shared": true,
				"invisible": false
			}
		},
		"acme__opensslConfigDefault": {
			"timeStamp": "2020-05-09T05:39:47.000Z",
			"attributes": {
				"invisible": true,
				"preemptive": "capable",
				"shared": false
			}
		},
		"ENV_isv17OrAbove": {
			"timeStamp": "2020-05-09T05:39:47.000Z",
			"attributes": {
				"invisible": true,
				"preemptive": "capable",
				"shared": false
			}
		},
		"acme__accountKeyDelete": {
			"timeStamp": "2020-05-09T05:39:46.000Z",
			"attributes": {
				"invisible": true,
				"shared": false
			}
		},
		"acme__httpHeaderSignature": {
			"timeStamp": "2020-05-09T05:39:47.000Z",
			"attributes": {
				"invisible": true,
				"shared": false
			}
		},
		"acme_READ_ME": {
			"timeStamp": "2020-05-09T05:39:47.000Z",
			"attributes": {
				"shared": true,
				"invisible": false
			}
		},
		"Méthode 242": {
			"timeStamp": "2020-10-09T16:52:56.397Z"
		},
		"acme_rsakeyPairGenerate": {
			"timeStamp": "2020-05-09T05:39:47.000Z",
			"attributes": {
				"shared": true,
				"invisible": false
			}
		},
		"acme__httpHeaderGetValForKey": {
			"timeStamp": "2020-05-09T05:39:46.000Z",
			"attributes": {
				"invisible": true,
				"shared": false
			}
		},
		"OB_jsonBlobParse": {
			"timeStamp": "2020-05-09T05:39:48.000Z",
			"attributes": {
				"invisible": true,
				"preemptive": "capable",
				"shared": false
			}
		},
		"ENV_is64bits": {
			"timeStamp": "2020-05-09T05:39:47.000Z",
			"attributes": {
				"invisible": true,
				"preemptive": "capable",
				"shared": false
			}
		},
		"acme__httpServerRequestToObject": {
			"timeStamp": "2020-05-09T05:39:47.000Z",
			"attributes": {
				"invisible": true,
				"preemptive": "capable",
				"shared": false
			}
		},
		"_cert_accountCreate": {
			"timeStamp": "2020-05-09T05:39:46.000Z",
			"attributes": {
				"shared": false,
				"invisible": true
			}
		},
		"acme__httpRequestHeaderCommon": {
			"timeStamp": "2020-05-09T05:39:47.000Z",
			"attributes": {
				"invisible": true,
				"shared": false
			}
		},
		"acme__httpClientOptionsSet": {
			"timeStamp": "2020-05-09T05:39:46.000Z",
			"attributes": {
				"invisible": true,
				"shared": false
			}
		},
		"acme_newOrderAndInstall": {
			"timeStamp": "2020-05-09T05:39:47.000Z",
			"attributes": {
				"shared": true,
				"invisible": false
			}
		},
		"_cert_renewAuto": {
			"timeStamp": "2020-05-09T05:39:46.000Z",
			"attributes": {
				"shared": false,
				"invisible": true
			}
		},
		"acme__dateFormatIso8601": {
			"timeStamp": "2020-05-09T05:39:46.000Z",
			"attributes": {
				"invisible": true,
				"shared": false
			}
		},
		"acme_accountObjectGet": {
			"timeStamp": "2020-05-09T05:39:47.000Z",
			"attributes": {
				"shared": true,
				"invisible": false
			}
		},
		"OB_newObject": {
			"timeStamp": "2020-05-09T05:39:48.000Z",
			"attributes": {
				"invisible": true,
				"preemptive": "capable",
				"shared": false
			}
		},
		"acme__keysKeyPairFilepathGet": {
			"timeStamp": "2020-05-09T05:39:47.000Z",
			"attributes": {
				"invisible": true,
				"shared": false
			}
		},
		"acme__logWorker": {
			"timeStamp": "2020-05-09T05:39:47.000Z",
			"attributes": {
				"invisible": true,
				"preemptive": "capable",
				"shared": false
			}
		},
		"acme_webServerStop": {
			"timeStamp": "2020-05-09T05:39:47.000Z",
			"attributes": {
				"shared": true,
				"invisible": false
			}
		},
		"acme__directoryUrlGet": {
			"timeStamp": "2020-05-09T05:39:46.000Z",
			"attributes": {
				"invisible": true,
				"shared": false
			}
		},
		"acme_certToText": {
			"timeStamp": "2020-05-09T05:39:47.000Z",
			"attributes": {
				"shared": true,
				"invisible": false
			}
		},
		"acme_directoryUrlGet": {
			"timeStamp": "2020-05-09T05:39:47.000Z",
			"attributes": {
				"shared": true,
				"invisible": false
			}
		},
		"acme__jwsObjectSign": {
			"timeStamp": "2020-05-09T05:39:47.000Z",
			"attributes": {
				"invisible": true,
				"shared": false
			}
		},
		"acme__keyFileProtect": {
			"timeStamp": "2020-05-09T05:39:47.000Z",
			"attributes": {
				"invisible": true,
				"shared": false
			}
		},
		"acme_certChainToText": {
			"timeStamp": "2020-05-09T05:39:47.000Z",
			"attributes": {
				"shared": true,
				"invisible": false
			}
		},
		"acme__httpServerRequestHdrGet": {
			"timeStamp": "2020-05-09T05:39:47.000Z",
			"attributes": {
				"invisible": true,
				"shared": false
			}
		},
		"acme__execbitForce": {
			"timeStamp": "2020-05-09T05:39:46.000Z",
			"attributes": {
				"invisible": true,
				"shared": false
			}
		},
		"acme__notify": {
			"timeStamp": "2020-05-09T05:39:47.000Z",
			"attributes": {
				"invisible": true,
				"shared": false
			}
		},
		"LONG_isEven": {
			"timeStamp": "2020-05-09T05:39:48.000Z",
			"attributes": {
				"invisible": true,
				"preemptive": "capable",
				"shared": false
			}
		},
		"acme_certificateGetAndInstall": {
			"timeStamp": "2020-05-09T05:39:47.000Z",
			"attributes": {
				"shared": true,
				"invisible": false
			}
		},
		"acme__keyPairRsaGenerate": {
			"timeStamp": "2020-05-09T05:39:47.000Z",
			"attributes": {
				"invisible": true,
				"shared": false
			}
		},
		"acme__timestamp": {
			"timeStamp": "2020-05-09T05:39:47.000Z",
			"attributes": {
				"invisible": true,
				"shared": false
			}
		},
		"UTL_base64UrlSafeEncode": {
			"timeStamp": "2020-05-09T05:39:48.000Z",
			"attributes": {
				"invisible": true,
				"preemptive": "capable",
				"shared": false
			}
		},
		"TXT_explodeFast": {
			"timeStamp": "2020-05-09T05:39:48.000Z",
			"attributes": {
				"invisible": true,
				"preemptive": "capable",
				"shared": false
			}
		},
		"acme__openSslSha256": {
			"timeStamp": "2020-05-09T05:39:47.000Z",
			"attributes": {
				"invisible": true,
				"shared": false
			}
		},
		"acme__httpHeadersToObject": {
			"timeStamp": "2020-05-09T05:39:47.000Z",
			"attributes": {
				"invisible": true,
				"shared": false
			}
		},
		"acme__openssl4dVersion": {
			"timeStamp": "2020-05-09T05:39:47.000Z",
			"attributes": {
				"invisible": true,
				"preemptive": "capable",
				"shared": false
			}
		},
		"acme_digestFile": {
			"timeStamp": "2020-05-09T05:39:47.000Z",
			"attributes": {
				"shared": true,
				"invisible": false
			}
		},
		"acme_webServerRestart": {
			"timeStamp": "2020-05-09T05:39:47.000Z",
			"attributes": {
				"shared": true,
				"invisible": false
			}
		},
		"acme__pemFormatChainToArrayTest": {
			"timeStamp": "2020-05-09T05:39:47.000Z",
			"attributes": {
				"invisible": true,
				"shared": false
			}
		},
		"acme__newNonceTest": {
			"timeStamp": "2020-05-09T05:39:47.000Z",
			"attributes": {
				"invisible": true,
				"shared": false
			}
		},
		"Méthode 154": {
			"timeStamp": "2020-05-09T05:39:48.000Z",
			"attributes": {
				"invisible": true,
				"shared": false
			}
		},
		"acme__opensslCertToTexttest": {
			"timeStamp": "2020-05-09T05:39:47.000Z",
			"attributes": {
				"invisible": true,
				"shared": false
			}
		},
		"Méthode 197": {
			"timeStamp": "2020-05-09T05:39:48.000Z",
			"attributes": {
				"invisible": true,
				"shared": false
			}
		},
		"Méthode 222": {
			"timeStamp": "2020-05-09T05:39:48.000Z",
			"attributes": {
				"shared": false,
				"invisible": true
			}
		},
		"acme__opensslCsrConvertFormat": {
			"timeStamp": "2020-05-09T05:39:47.000Z",
			"attributes": {
				"invisible": true,
				"shared": false
			}
		},
		"UTL_base64UrlSafeDecode": {
			"timeStamp": "2020-05-09T05:39:48.000Z",
			"attributes": {
				"invisible": true,
				"preemptive": "capable",
				"shared": false
			}
		},
		"acme__newAccountTest": {
			"timeStamp": "2020-05-09T05:39:47.000Z",
			"attributes": {
				"invisible": true,
				"shared": false
			}
		},
		"acme_certActiveDirPathGet": {
			"timeStamp": "2020-07-30T08:46:08.000Z",
			"attributes": {
				"shared": true,
				"invisible": false
			}
		},
		"acme__keyPrivExponentGet": {
			"timeStamp": "2020-05-09T05:39:47.000Z",
			"attributes": {
				"invisible": true,
				"shared": false
			}
		},
		"acme__challengeRequest": {
			"timeStamp": "2020-05-09T05:39:46.000Z",
			"attributes": {
				"invisible": true,
				"shared": false
			}
		},
		"Méthode 196": {
			"timeStamp": "2020-05-09T05:39:48.000Z",
			"attributes": {
				"invisible": true,
				"shared": false
			}
		},
		"acme__httpServerRequestMethod": {
			"timeStamp": "2020-05-09T05:39:47.000Z",
			"attributes": {
				"invisible": true,
				"shared": false
			}
		},
		"acme__nonceGet": {
			"timeStamp": "2020-05-09T05:39:47.000Z",
			"attributes": {
				"invisible": true,
				"shared": false
			}
		},
		"acme__httpServerRequestUrl": {
			"timeStamp": "2020-05-09T05:39:47.000Z",
			"attributes": {
				"invisible": true,
				"shared": false
			}
		},
		"acme__opensslConfigDefaultSub": {
			"timeStamp": "2020-05-09T05:39:47.000Z",
			"attributes": {
				"invisible": true,
				"preemptive": "capable",
				"shared": false
			}
		},
		"acme_onWebConnection": {
			"timeStamp": "2020-05-09T05:39:47.000Z",
			"attributes": {
				"shared": true,
				"preemptive": "capable",
				"invisible": false
			}
		},
		"acme__webHstsStop": {
			"timeStamp": "2020-05-09T05:39:47.000Z",
			"attributes": {
				"invisible": true,
				"shared": false
			}
		},
		"acme__nonceHeaderGet": {
			"timeStamp": "2020-05-09T05:39:47.000Z",
			"attributes": {
				"invisible": true,
				"shared": false
			}
		},
		"acme_componentVersionGet": {
			"timeStamp": "2020-10-09T17:13:31.258Z",
			"attributes": {
				"shared": true,
				"preemptive": "capable",
				"invisible": false
			}
		},
		"acme__opensslCertToText": {
			"timeStamp": "2020-05-09T05:39:47.000Z",
			"attributes": {
				"invisible": true,
				"shared": false
			}
		},
		"Méthode 234": {
			"timeStamp": "2020-05-09T05:39:48.000Z",
			"attributes": {
				"shared": false,
				"invisible": true
			}
		},
		"Méthode 220": {
			"timeStamp": "2020-05-09T05:39:48.000Z",
			"attributes": {
				"shared": false,
				"invisible": true
			}
		},
		"DAT_iso8601Diff": {
			"timeStamp": "2020-05-09T05:39:47.000Z",
			"attributes": {
				"invisible": true,
				"preemptive": "capable",
				"shared": false
			}
		},
		"acme__orderStatusGet": {
			"timeStamp": "2020-05-09T05:39:47.000Z",
			"attributes": {
				"invisible": true,
				"shared": false
			}
		},
		"Méthode 195": {
			"timeStamp": "2020-05-09T05:39:48.000Z",
			"attributes": {
				"invisible": true,
				"shared": false
			}
		},
		"Méthode 142": {
			"timeStamp": "2020-05-09T05:39:48.000Z",
			"attributes": {
				"invisible": true,
				"shared": false
			}
		},
		"Méthode 156": {
			"timeStamp": "2020-05-09T05:39:48.000Z",
			"attributes": {
				"invisible": true,
				"shared": false
			}
		},
		"acme_certificateGet": {
			"timeStamp": "2020-05-09T05:39:47.000Z",
			"attributes": {
				"shared": true,
				"invisible": false
			}
		},
		"acme_logHttpServerInfos": {
			"timeStamp": "2020-05-09T05:39:47.000Z",
			"attributes": {
				"shared": true,
				"invisible": false
			}
		},
		"ENV__isComponent": {
			"timeStamp": "2020-05-09T05:39:47.000Z",
			"attributes": {
				"invisible": true,
				"preemptive": "capable",
				"shared": false
			}
		},
		"Méthode 146": {
			"timeStamp": "2020-05-09T05:39:48.000Z",
			"attributes": {
				"invisible": true,
				"shared": false
			}
		},
		"acme_newAccountObject": {
			"timeStamp": "2020-05-09T05:39:47.000Z",
			"attributes": {
				"shared": true,
				"invisible": false
			}
		},
		"acme__archiveFile": {
			"timeStamp": "2020-05-09T05:39:46.000Z",
			"attributes": {
				"invisible": true,
				"shared": false
			}
		},
		"FS_pathToParent": {
			"timeStamp": "2020-05-09T05:39:47.000Z",
			"attributes": {
				"invisible": true,
				"preemptive": "capable",
				"shared": false
			}
		},
		"acme_directoryMetaPropertyGet": {
			"timeStamp": "2020-05-09T05:39:47.000Z",
			"attributes": {
				"shared": true,
				"invisible": false
			}
		},
		"UTL_textToDocument": {
			"timeStamp": "2020-05-09T05:39:48.000Z",
			"attributes": {
				"invisible": true,
				"preemptive": "capable",
				"shared": false
			}
		},
		"acme_csrAltnamesNew": {
			"timeStamp": "2020-05-09T05:39:47.000Z",
			"attributes": {
				"shared": true,
				"invisible": false
			}
		},
		"acme__httpServerRequestVersion": {
			"timeStamp": "2020-05-09T05:39:47.000Z",
			"attributes": {
				"invisible": true,
				"shared": false
			}
		},
		"Méthode 224": {
			"timeStamp": "2020-05-09T05:39:48.000Z",
			"attributes": {
				"shared": false,
				"invisible": true
			}
		},
		"Méthode 230": {
			"timeStamp": "2020-05-09T05:39:48.000Z",
			"attributes": {
				"shared": false,
				"invisible": true
			}
		},
		"acme_csrGenerateAndSign": {
			"timeStamp": "2020-05-09T05:39:47.000Z",
			"attributes": {
				"shared": true,
				"invisible": false
			}
		},
		"acme_workingDirSet": {
			"timeStamp": "2020-05-09T05:39:47.000Z",
			"attributes": {
				"shared": true,
				"invisible": false
			}
		},
		"acme__removeLastWhitespaces": {
			"timeStamp": "2020-05-09T05:39:47.000Z",
			"attributes": {
				"invisible": true,
				"preemptive": "capable",
				"shared": false
			}
		},
		"HEX_blobPtrToHexStr": {
			"timeStamp": "2020-05-09T05:39:47.000Z",
			"attributes": {
				"invisible": true,
				"preemptive": "capable",
				"shared": false
			}
		},
		"acme_onWebAuthentication": {
			"timeStamp": "2020-05-09T05:39:47.000Z",
			"attributes": {
				"shared": true,
				"preemptive": "capable",
				"invisible": false
			}
		},
		"Méthode 190": {
			"timeStamp": "2020-05-09T05:39:48.000Z",
			"attributes": {
				"invisible": true,
				"shared": false
			}
		},
		"acme_csrReqConfObjectNew": {
			"timeStamp": "2020-05-09T05:39:47.000Z",
			"attributes": {
				"shared": true,
				"invisible": false
			}
		},
		"Méthode 151": {
			"timeStamp": "2020-05-09T05:39:48.000Z",
			"attributes": {
				"invisible": true,
				"shared": false
			}
		},
		"Méthode 192": {
			"timeStamp": "2020-05-09T05:39:48.000Z",
			"attributes": {
				"invisible": true,
				"shared": false
			}
		},
		"UTL_durationMsDebug": {
			"timeStamp": "2020-05-09T05:39:48.000Z",
			"attributes": {
				"invisible": true,
				"preemptive": "capable",
				"shared": false
			}
		},
		"ENV_onWindows": {
			"timeStamp": "2020-05-09T05:39:47.000Z",
			"attributes": {
				"invisible": true,
				"preemptive": "capable",
				"shared": false
			}
		},
		"acme__opensslVersionGet": {
			"timeStamp": "2020-05-09T05:39:47.000Z",
			"attributes": {
				"invisible": true,
				"shared": false
			}
		},
		"acme__opensslToText": {
			"timeStamp": "2020-05-09T05:39:47.000Z",
			"attributes": {
				"invisible": true,
				"shared": false
			}
		},
		"Méthode 226": {
			"timeStamp": "2020-05-09T05:39:48.000Z",
			"attributes": {
				"shared": false,
				"invisible": true
			}
		},
		"acme_sslCipherListSet": {
			"timeStamp": "2020-05-09T05:39:47.000Z",
			"attributes": {
				"shared": true,
				"invisible": false
			}
		},
		"Méthode 232": {
			"timeStamp": "2020-05-09T05:39:48.000Z",
			"attributes": {
				"shared": false,
				"invisible": true
			}
		},
		"acme_authorizationGet": {
			"timeStamp": "2020-05-09T05:39:47.000Z",
			"attributes": {
				"shared": true,
				"invisible": false
			}
		},
		"acme__errHdlrToDevNull": {
			"timeStamp": "2020-05-09T05:39:46.000Z",
			"attributes": {
				"invisible": true,
				"shared": false
			}
		},
		"Méthode 193": {
			"timeStamp": "2020-05-09T05:39:48.000Z",
			"attributes": {
				"invisible": true,
				"shared": false
			}
		},
		"acme__selftests": {
			"timeStamp": "2020-05-09T05:39:47.000Z",
			"attributes": {
				"invisible": true,
				"shared": false
			}
		},
		"acme__initSub": {
			"timeStamp": "2020-10-01T20:53:43.591Z",
			"attributes": {
				"invisible": true,
				"shared": false
			}
		},
		"Méthode 178": {
			"timeStamp": "2020-05-09T05:39:48.000Z",
			"attributes": {
				"invisible": true,
				"shared": false
			}
		},
		"acme__logInit": {
			"timeStamp": "2020-05-09T05:39:47.000Z",
			"attributes": {
				"invisible": true,
				"shared": false
			}
		},
		"acme__init": {
			"timeStamp": "2020-10-01T20:48:15.239Z",
			"attributes": {
				"invisible": true,
				"shared": false
			}
		},
		"acme__webHstsStart": {
			"timeStamp": "2020-05-09T05:39:47.000Z",
			"attributes": {
				"invisible": true,
				"shared": false
			}
		},
		"acme_challengeStartTest": {
			"timeStamp": "2020-05-09T05:39:47.000Z",
			"attributes": {
				"invisible": false,
				"shared": true
			}
		},
		"acme_orderFinalizeTest": {
			"timeStamp": "2020-05-09T05:39:47.000Z",
			"attributes": {
				"shared": true,
				"invisible": false
			}
		},
		"Méthode 161": {
			"timeStamp": "2020-05-09T05:39:48.000Z",
			"attributes": {
				"invisible": true,
				"shared": false
			}
		},
		"Méthode 175": {
			"timeStamp": "2020-05-09T05:39:48.000Z",
			"attributes": {
				"invisible": true,
				"shared": false
			}
		},
		"acme_certDateValidyInSeconds": {
			"timeStamp": "2020-05-09T05:39:47.000Z",
			"attributes": {
				"shared": true,
				"invisible": false
			}
		},
		"acme__jwkThumbprint": {
			"timeStamp": "2020-05-09T05:39:47.000Z",
			"attributes": {
				"invisible": true,
				"shared": false
			}
		},
		"acme__jsonContentType": {
			"timeStamp": "2020-05-09T05:39:47.000Z",
			"attributes": {
				"invisible": true,
				"shared": false
			}
		},
		"acme__objectToBlob": {
			"timeStamp": "2020-05-09T05:39:47.000Z",
			"attributes": {
				"invisible": true,
				"shared": false
			}
		},
		"acme__challengeDirCleanup": {
			"timeStamp": "2020-05-09T05:39:46.000Z",
			"attributes": {
				"invisible": true,
				"shared": false
			}
		},
		"UTL_textToFile": {
			"timeStamp": "2020-05-09T05:39:48.000Z",
			"attributes": {
				"invisible": true,
				"preemptive": "capable",
				"shared": false
			}
		},
		"Méthode 202": {
			"timeStamp": "2020-05-09T05:39:48.000Z",
			"attributes": {
				"invisible": true,
				"shared": false
			}
		},
		"acme__opensslCsrNewtest": {
			"timeStamp": "2020-05-09T05:39:47.000Z",
			"attributes": {
				"invisible": true,
				"shared": false
			}
		},
		"acme_directoryGet": {
			"timeStamp": "2020-05-09T05:39:47.000Z",
			"attributes": {
				"shared": true,
				"invisible": false
			}
		},
		"DBG__dbgInitAuto": {
			"timeStamp": "2020-05-09T05:39:47.000Z",
			"attributes": {
				"invisible": true,
				"shared": false
			}
		},
		"acme__keyPrivModulusGet": {
			"timeStamp": "2020-10-09T16:53:22.127Z",
			"attributes": {
				"invisible": true,
				"shared": false
			}
		},
		"acme__removeLastLFTest": {
			"timeStamp": "2020-05-09T05:39:47.000Z",
			"attributes": {
				"invisible": true,
				"shared": false
			}
		},
		"HEX_hexByteStrToByteInteger": {
			"timeStamp": "2020-05-09T05:39:47.000Z",
			"attributes": {
				"invisible": true,
				"preemptive": "capable",
				"shared": false
			}
		},
		"ENV_isPreemptive": {
			"timeStamp": "2020-05-09T05:39:47.000Z",
			"attributes": {
				"invisible": true,
				"preemptive": "capable",
				"shared": false
			}
		},
		"acme__executeBatFile": {
			"timeStamp": "2020-05-09T05:39:46.000Z",
			"attributes": {
				"invisible": true,
				"shared": false
			}
		},
		"acme__openSslCmd": {
			"timeStamp": "2020-10-09T17:01:16.127Z",
			"attributes": {
				"invisible": true,
				"shared": false
			}
		},
		"FS_pathToFilename": {
			"timeStamp": "2020-05-09T05:39:47.000Z",
			"attributes": {
				"invisible": true,
				"preemptive": "capable",
				"shared": false
			}
		},
		"acme__challengeReqUrlMatchT": {
			"timeStamp": "2020-05-09T05:39:46.000Z",
			"attributes": {
				"invisible": true,
				"shared": false
			}
		},
		"Méthode 162": {
			"timeStamp": "2020-05-09T05:39:48.000Z",
			"attributes": {
				"invisible": true,
				"shared": false
			}
		},
		"acme_directoryUrlSet": {
			"timeStamp": "2020-05-09T05:39:47.000Z",
			"attributes": {
				"shared": true,
				"invisible": false
			}
		},
		"acme_newOrderObject": {
			"timeStamp": "2020-05-09T05:39:47.000Z",
			"attributes": {
				"shared": true,
				"invisible": false
			}
		},
		"acme_orderDirPathGet": {
			"timeStamp": "2020-05-09T05:39:47.000Z",
			"attributes": {
				"shared": true,
				"invisible": false
			}
		},
		"acme_accountStatus": {
			"timeStamp": "2020-05-09T05:39:47.000Z",
			"attributes": {
				"shared": true,
				"invisible": false
			}
		},
		"Méthode 201": {
			"timeStamp": "2020-05-09T05:39:48.000Z",
			"attributes": {
				"invisible": true,
				"shared": false
			}
		},
		"Méthode 229": {
			"timeStamp": "2020-05-09T05:39:48.000Z",
			"attributes": {
				"shared": false,
				"invisible": true
			}
		},
		"acme__csrReqConfObjectToTextSub": {
			"timeStamp": "2020-05-09T05:39:46.000Z",
			"attributes": {
				"invisible": true,
				"shared": false
			}
		},
		"acme__errorHdlr": {
			"timeStamp": "2020-05-09T05:39:46.000Z",
			"attributes": {
				"invisible": true,
				"shared": false
			}
		},
		"acme_orderAuthorisationProcess": {
			"timeStamp": "2020-05-09T05:39:47.000Z",
			"attributes": {
				"shared": true,
				"invisible": false
			}
		},
		"acme__opensslCsrToText": {
			"timeStamp": "2020-05-09T05:39:47.000Z",
			"attributes": {
				"invisible": true,
				"shared": false
			}
		},
		"Méthode 188": {
			"timeStamp": "2020-05-09T05:39:48.000Z",
			"attributes": {
				"invisible": true,
				"shared": false
			}
		},
		"Méthode 177": {
			"timeStamp": "2020-05-09T05:39:48.000Z",
			"attributes": {
				"invisible": true,
				"shared": false
			}
		},
		"acme__urlLocationIdGet": {
			"timeStamp": "2020-05-09T05:39:47.000Z",
			"attributes": {
				"invisible": true,
				"shared": false
			}
		},
		"DAT_iso8601DateTimeGmt": {
			"timeStamp": "2020-05-09T05:39:47.000Z",
			"attributes": {
				"invisible": true,
				"preemptive": "capable",
				"shared": false
			}
		},
		"acme_identifierObjectNew": {
			"timeStamp": "2020-05-09T05:39:47.000Z",
			"attributes": {
				"shared": true,
				"invisible": false
			}
		},
		"acme_certCheckEnd": {
			"timeStamp": "2020-05-09T05:39:47.000Z",
			"attributes": {
				"shared": true,
				"invisible": false
			}
		},
		"acme__logEvent": {
			"timeStamp": "2020-05-09T05:39:47.000Z",
			"attributes": {
				"invisible": true,
				"preemptive": "capable",
				"shared": false
			}
		},
		"Méthode 205": {
			"timeStamp": "2020-05-09T05:39:48.000Z",
			"attributes": {
				"shared": false,
				"invisible": true
			}
		},
		"Méthode 211": {
			"timeStamp": "2020-05-09T05:39:48.000Z",
			"attributes": {
				"shared": false,
				"invisible": true
			}
		},
		"acme__compilerG": {
			"timeStamp": "2020-05-09T05:39:46.000Z",
			"attributes": {
				"invisible": true,
				"shared": false
			}
		},
		"acme__keysKeyPairFileGenerate": {
			"timeStamp": "2020-05-09T05:39:47.000Z",
			"attributes": {
				"invisible": true,
				"shared": false
			}
		},
		"Méthode 238": {
			"timeStamp": "2020-05-09T05:39:48.000Z",
			"attributes": {
				"shared": false,
				"invisible": true
			}
		},
		"Méthode 204": {
			"timeStamp": "2020-05-09T05:39:48.000Z",
			"attributes": {
				"invisible": true,
				"shared": false
			}
		},
		"acme__tokenToFilenameSafe": {
			"timeStamp": "2020-05-09T05:39:47.000Z",
			"attributes": {
				"invisible": true,
				"preemptive": "capable",
				"shared": false
			}
		},
		"acme__keysKeyPairFileGet": {
			"timeStamp": "2020-05-09T05:39:47.000Z",
			"attributes": {
				"invisible": true,
				"shared": false
			}
		},
		"HEX_hexTextToBlob": {
			"timeStamp": "2020-05-09T05:39:48.000Z",
			"attributes": {
				"invisible": true,
				"preemptive": "capable",
				"shared": false
			}
		},
		"Méthode 166": {
			"timeStamp": "2020-05-09T05:39:48.000Z",
			"attributes": {
				"invisible": true,
				"shared": false
			}
		},
		"Méthode 172": {
			"timeStamp": "2020-05-09T05:39:48.000Z",
			"attributes": {
				"invisible": true,
				"shared": false
			}
		},
		"UTL_pathToPosixConvert": {
			"timeStamp": "2020-05-09T05:39:48.000Z",
			"attributes": {
				"invisible": true,
				"preemptive": "capable",
				"shared": false
			}
		},
		"Méthode 164": {
			"timeStamp": "2020-05-09T05:39:48.000Z",
			"attributes": {
				"invisible": true,
				"shared": false
			}
		},
		"Méthode 170": {
			"timeStamp": "2020-05-09T05:39:48.000Z",
			"attributes": {
				"invisible": true,
				"shared": false
			}
		},
		"acme__opensslCsrNew": {
			"timeStamp": "2020-05-09T05:39:47.000Z",
			"attributes": {
				"invisible": true,
				"shared": false
			}
		},
		"acme_httpChallengePrepare": {
			"timeStamp": "2020-05-09T05:39:47.000Z",
			"attributes": {
				"shared": true,
				"invisible": false
			}
		},
		"acme__logWorkerErrHdlr": {
			"timeStamp": "2020-05-09T05:39:47.000Z",
			"attributes": {
				"invisible": true,
				"preemptive": "capable",
				"shared": false
			}
		},
		"acme_orderGet": {
			"timeStamp": "2020-05-09T05:39:47.000Z",
			"attributes": {
				"shared": true,
				"invisible": false
			}
		},
		"acme__errorHandler": {
			"timeStamp": "2020-05-09T05:39:46.000Z",
			"attributes": {
				"invisible": true,
				"shared": false
			}
		},
		"DAT__tsBaseDate": {
			"timeStamp": "2020-05-09T05:39:47.000Z",
			"attributes": {
				"invisible": true,
				"preemptive": "capable",
				"shared": false
			}
		},
		"acme__errorHdlrAfter": {
			"timeStamp": "2020-05-09T05:39:46.000Z",
			"attributes": {
				"invisible": true,
				"shared": false
			}
		},
		"UTL_durationDifference": {
			"timeStamp": "2020-05-09T05:39:48.000Z",
			"attributes": {
				"invisible": true,
				"preemptive": "capable",
				"shared": false
			}
		},
		"acme__pemFormatCheck": {
			"timeStamp": "2020-05-09T05:39:47.000Z",
			"attributes": {
				"invisible": true,
				"shared": false
			}
		},
		"acme_newAccount": {
			"timeStamp": "2020-05-09T05:39:47.000Z",
			"attributes": {
				"shared": true,
				"invisible": false
			}
		},
		"Compiler_Variables_Inter": {
			"timeStamp": "2020-05-09T05:39:47.000Z",
			"attributes": {
				"invisible": true,
				"shared": false
			}
		},
		"Compiler_Variables": {
			"timeStamp": "2020-05-09T05:39:47.000Z",
			"attributes": {
				"invisible": true,
				"shared": false
			}
		},
		"acme_orderFinalize": {
			"timeStamp": "2020-05-09T05:39:47.000Z",
			"attributes": {
				"shared": true,
				"invisible": false
			}
		},
		"acme__pemFormatCheckTest": {
			"timeStamp": "2020-05-09T05:39:47.000Z",
			"attributes": {
				"invisible": true,
				"shared": false
			}
		},
		"acme__protectedObjGet": {
			"timeStamp": "2020-05-09T05:39:47.000Z",
			"attributes": {
				"invisible": true,
				"shared": false
			}
		},
		"acme__openSslSignKeyPath": {
			"timeStamp": "2020-05-09T05:39:47.000Z",
			"attributes": {
				"invisible": true,
				"shared": false
			}
		},
		"acme_pemFormatChainToArray": {
			"timeStamp": "2020-05-09T05:39:47.000Z",
			"attributes": {
				"shared": true,
				"invisible": false
			}
		},
		"acme__accountInit": {
			"timeStamp": "2020-05-09T05:39:46.000Z",
			"attributes": {
				"invisible": true,
				"shared": false
			}
		},
		"acme_sslCipherListGet": {
			"timeStamp": "2020-05-09T05:39:47.000Z",
			"attributes": {
				"shared": true,
				"preemptive": "capable",
				"invisible": false
			}
		},
		"acme__certCurrentGet_": {
			"timeStamp": "2020-05-09T05:39:46.000Z",
			"attributes": {
				"invisible": true,
				"shared": false
			}
		},
		"acme_certificateAsTextInstall": {
			"timeStamp": "2020-05-09T05:39:47.000Z",
			"attributes": {
				"shared": true,
				"invisible": false
			}
		},
		"acme_csrSubjectAutoFromDomains": {
			"timeStamp": "2020-05-09T05:39:47.000Z",
			"attributes": {
				"shared": true,
				"invisible": false
			}
		},
		"acme_httpChallengePrepareTest": {
			"timeStamp": "2020-05-09T05:39:47.000Z",
			"attributes": {
				"shared": true,
				"invisible": false
			}
		},
		"UTL_initAuto": {
			"timeStamp": "2020-05-09T05:39:48.000Z",
			"attributes": {
				"invisible": true,
				"shared": false
			}
		},
		"acme_sampleCode": {
			"timeStamp": "2020-05-09T05:39:47.000Z",
			"attributes": {
				"shared": true,
				"invisible": false
			}
		},
		"acme__initG": {
			"timeStamp": "2020-05-09T05:39:47.000Z",
			"attributes": {
				"invisible": true,
				"shared": false
			}
		},
		"acme_workingDirGet": {
			"timeStamp": "2020-05-09T05:39:47.000Z",
			"attributes": {
				"shared": true,
				"invisible": false
			}
		},
		"Compiler_Methods": {
			"timeStamp": "2020-05-09T05:39:47.000Z",
			"attributes": {
				"invisible": true,
				"shared": false
			}
		},
		"acme__opensslPathGet": {
			"timeStamp": "2020-05-09T05:39:47.000Z",
			"attributes": {
				"invisible": true,
				"preemptive": "capable",
				"shared": false
			}
		},
		"acme__accountInitSub": {
			"timeStamp": "2020-05-09T05:39:46.000Z",
			"attributes": {
				"invisible": true,
				"shared": false
			}
		},
		"_cert_accountInit": {
			"timeStamp": "2020-05-09T05:39:46.000Z",
			"attributes": {
				"shared": false,
				"invisible": true
			}
		},
		"TXT_endOfLineNormalize": {
			"timeStamp": "2020-05-09T05:39:48.000Z",
			"attributes": {
				"invisible": true,
				"preemptive": "capable",
				"shared": false
			}
		},
		"acme__log": {
			"timeStamp": "2020-05-09T05:39:47.000Z",
			"attributes": {
				"invisible": true,
				"preemptive": "capable",
				"shared": false
			}
		},
		"DAT_tsNew": {
			"timeStamp": "2020-05-09T05:39:47.000Z",
			"attributes": {
				"invisible": true,
				"preemptive": "capable",
				"shared": false
			}
		},
		"HEX_hexCharToInt": {
			"timeStamp": "2020-05-09T05:39:48.000Z",
			"attributes": {
				"invisible": true,
				"preemptive": "capable",
				"shared": false
			}
		},
		"acme__csrReqConfObjectToText": {
			"timeStamp": "2020-05-09T05:39:46.000Z",
			"attributes": {
				"invisible": true,
				"shared": false
			}
		},
		"TXT_isEqualStrict": {
			"timeStamp": "2020-05-09T05:39:48.000Z",
			"attributes": {
				"invisible": true,
				"preemptive": "capable",
				"shared": false
			}
		},
		"UUID_new": {
			"timeStamp": "2020-05-09T05:39:48.000Z",
			"attributes": {
				"invisible": true,
				"preemptive": "capable",
				"shared": false
			}
		},
		"acme__domainReverse": {
			"timeStamp": "2020-05-09T05:39:46.000Z",
			"attributes": {
				"invisible": true,
				"shared": false
			}
		},
		"acme__xdocInit": {
			"timeStamp": "2020-05-09T05:39:47.000Z",
			"attributes": {
				"invisible": true,
				"shared": false
			}
		},
		"acme_orderAuthorisationWait": {
			"timeStamp": "2020-05-09T05:39:47.000Z",
			"attributes": {
				"shared": true,
				"invisible": false
			}
		},
		"acme__challengeReqUrlMatch": {
			"timeStamp": "2020-05-09T05:39:46.000Z",
			"attributes": {
				"invisible": true,
				"shared": false
			}
		},
		"acme__keyPairRsaGenerateTest": {
			"timeStamp": "2020-05-09T05:39:47.000Z",
			"attributes": {
				"invisible": true,
				"shared": false
			}
		},
		"_cert_renew": {
			"timeStamp": "2020-05-09T05:39:46.000Z",
			"attributes": {
				"shared": false,
				"invisible": true
			}
		},
		"acme__varPtrDebug": {
			"timeStamp": "2020-10-09T17:10:50.418Z",
			"attributes": {
				"invisible": true
			}
		},
		"acme_opensslCsrConvertFormatTes": {
			"timeStamp": "2020-05-09T05:39:47.000Z",
			"attributes": {
				"invisible": false,
				"shared": true
			}
		},
		"acme__opensslModulus": {
			"timeStamp": "2020-05-09T05:39:47.000Z",
			"attributes": {
				"invisible": true,
				"shared": false
			}
		},
		"acme__compiler": {
			"timeStamp": "2020-05-09T05:39:46.000Z",
			"attributes": {
				"invisible": true,
				"shared": false
			}
		},
		"acme_rsaCertSelfSignedCreate": {
			"timeStamp": "2020-05-09T05:39:47.000Z",
			"attributes": {
				"shared": true,
				"invisible": false
			}
		},
		"TXT_lineSepGetTest": {
			"timeStamp": "2020-05-09T05:39:48.000Z",
			"attributes": {
				"invisible": true,
				"preemptive": "capable",
				"shared": false
			}
		},
		"acme_certificateOrderAndInstall": {
			"timeStamp": "2020-05-09T05:39:47.000Z",
			"attributes": {
				"shared": true,
				"invisible": false
			}
		},
		"acme__errorLastGet": {
			"timeStamp": "2020-05-09T05:39:46.000Z",
			"attributes": {
				"invisible": true,
				"shared": false
			}
		},
		"acme_newOrder": {
			"timeStamp": "2020-05-09T05:39:47.000Z",
			"attributes": {
				"shared": true,
				"invisible": false
			}
		},
		"acme__errorHdlrBefore": {
			"timeStamp": "2020-05-09T05:39:46.000Z",
			"attributes": {
				"invisible": true,
				"shared": false
			}
		},
		"acme__nonceRefresh": {
			"timeStamp": "2020-05-09T05:39:47.000Z",
			"attributes": {
				"invisible": true,
				"shared": false
			}
		},
		"acme_certificateInstall": {
			"timeStamp": "2020-05-09T05:39:47.000Z",
			"attributes": {
				"shared": true,
				"invisible": false
			}
		},
		"TXT_regexGetMatchingGroup": {
			"timeStamp": "2020-05-09T05:39:48.000Z",
			"attributes": {
				"invisible": true,
				"preemptive": "capable",
				"shared": false
			}
		},
		"acme_accountStatusTest": {
			"timeStamp": "2020-05-09T05:39:47.000Z",
			"attributes": {
				"shared": true,
				"invisible": false
			}
		},
		"(Méthode 246)": {
			"timeStamp": "2020-10-09T16:52:18.988Z"
		},
		"(Méthode 270)": {
			"timeStamp": "2020-02-14T16:46:49.000Z",
			"attributes": {
				"invisible": true
			}
		},
		"(_acme__signRequest)": {
			"timeStamp": "2020-02-14T16:46:49.000Z",
			"attributes": {
				"invisible": true
			}
		},
		"(_acme__opensslExecBitForce)": {
			"timeStamp": "2020-10-01T11:40:51.503Z"
		},
		"(acme__execbitForceSub)": {
			"timeStamp": "2020-02-21T17:45:25.000Z",
			"attributes": {
				"invisible": true
			}
		},
		"(Méthode 184)": {
			"timeStamp": "2020-02-14T16:46:49.000Z",
			"attributes": {
				"invisible": true
			}
		},
		"(XDOC_run)": {
			"timeStamp": "2020-02-14T16:46:49.000Z",
			"attributes": {
				"invisible": true
			}
		},
		"(LPE__removeLastLF)": {
			"timeStamp": "2020-10-01T11:36:37.703Z"
		},
		"(Compiler_Arrays)": {
			"timeStamp": "2020-02-14T16:46:49.000Z",
			"attributes": {
				"invisible": true
			}
		},
		"(Méthode 248)": {
			"timeStamp": "2020-10-09T17:13:37.157Z"
		},
		"(Méthode 176)": {
			"timeStamp": "2020-02-14T16:46:49.000Z",
			"attributes": {
				"invisible": true
			}
		},
		"(acme_digestFileTest)": {
			"timeStamp": "2020-02-14T16:46:49.000Z",
			"attributes": {
				"invisible": true,
				"shared": true
			}
		},
		"(Méthode 183)": {
			"timeStamp": "2020-02-14T16:46:49.000Z",
			"attributes": {
				"invisible": true
			}
		},
		"(Méthode 245)": {
			"timeStamp": "2020-10-01T11:44:44.320Z"
		}
	}
}